flask_babel/__init__.py
flask_babel/_compat.py
flask_babel/speaklater.py
Flask_Babel-1.0.0.dist-info/LICENSE
Flask_Babel-1.0.0.dist-info/METADATA
Flask_Babel-1.0.0.dist-info/WHEEL
Flask_Babel-1.0.0.dist-info/top_level.txt
Flask_Babel-1.0.0.dist-info/RECORD
